latterdns/__init__.py
latterdns-0.3.0.dist-info/WHEEL
latterdns-0.3.0.dist-info/entry_points.txt
latterdns-0.3.0.dist-info/METADATA
latterdns-0.3.0.dist-info/RECORD
