Metadata-Version: 2.3
Name: latterdns
Version: 0.3.0
Summary: A lightweight DNS proxy designed to bypass DNS spoofing by exploiting timing differences between fake and legitimate packets
Keywords: dns,proxy,censorship,gfw,anti-censorship
Author: Amir Hosseini Nasab
Author-email: Amir Hosseini Nasab <awmirhn@gmail.com>
License: MIT
Classifier: Development Status :: 3 - Alpha
Classifier: Intended Audience :: Developers
Classifier: Intended Audience :: System Administrators
Classifier: License :: OSI Approved :: MIT License
Classifier: Programming Language :: Python :: 3
Classifier: Programming Language :: Python :: 3.14
Classifier: Topic :: Internet :: Name Service (DNS)
Classifier: Topic :: System :: Networking
Requires-Dist: click>=8.3.1
Requires-Python: >=3.14
Project-URL: Homepage, https://github.com/itsamirhn/latterdns
Project-URL: Issues, https://github.com/itsamirhn/latterdns/issues
Project-URL: Repository, https://github.com/itsamirhn/latterdns
